tklr/__init__.py
tklr/controller.py
tklr/help.py
tklr/item.py
tklr/list_colors.py
tklr/mask.py
tklr/migration.py
tklr/model.py
tklr/query.py
tklr/shared.py
tklr/tklr_env.py
tklr/use_system.py
tklr/versioning.py
tklr/view.py
tklr/view_dark.css
tklr/view_light.css
tklr/cli/main.py
tklr/scripts/simulate_midnight.py
tklr/sounds/alert.mp3
tklr_dgraham-0.0.44.dist-info/METADATA
tklr_dgraham-0.0.44.dist-info/WHEEL
tklr_dgraham-0.0.44.dist-info/entry_points.txt
tklr_dgraham-0.0.44.dist-info/top_level.txt
tklr_dgraham-0.0.44.dist-info/RECORD
