Metadata-Version: 2.4
Name: tklr-dgraham
Version: 0.0.44
Summary: Reminders Tickler / CLI and Textual UI
Author-email: Daniel Graham <dnlgrhm@gmail.com>
Requires-Python: <4.0,>=3.12
Requires-Dist: textual>=0.60
Requires-Dist: python-dateutil>=2.8.2
Requires-Dist: tzlocal>=5.3.1
Requires-Dist: certifi>=2024.2.2
Requires-Dist: packaging>=25.0
Requires-Dist: pydantic>=2.11.7
Requires-Dist: jinja2>=3.1.6
Requires-Dist: click>=8.2.1
Requires-Dist: lorem>=0.1.1
Requires-Dist: readchar>=4.2.1
Requires-Dist: numpy>=2.3.3
Requires-Dist: pyperclip>=1.11.0
Requires-Dist: tomlkit>=0.13.3
Provides-Extra: dev
Requires-Dist: lorem>=0.1.1; extra == "dev"
Requires-Dist: pre-commit>=3.6.0; extra == "dev"
Provides-Extra: test
Requires-Dist: pytest>=8.0.0; extra == "test"
Requires-Dist: pytest-cov>=4.1.0; extra == "test"
Requires-Dist: freezegun>=1.4.0; extra == "test"
Requires-Dist: pytest-mock>=3.12.0; extra == "test"
